LICENSE
MANIFEST.in
README.md
setup.py
OASYS1_ESRF_Extensions.egg-info/PKG-INFO
OASYS1_ESRF_Extensions.egg-info/SOURCES.txt
OASYS1_ESRF_Extensions.egg-info/dependency_links.txt
OASYS1_ESRF_Extensions.egg-info/entry_points.txt
OASYS1_ESRF_Extensions.egg-info/namespace_packages.txt
OASYS1_ESRF_Extensions.egg-info/not-zip-safe
OASYS1_ESRF_Extensions.egg-info/requires.txt
OASYS1_ESRF_Extensions.egg-info/top_level.txt
orangecontrib/__init__.py
orangecontrib/esrf/__init__.py
orangecontrib/esrf/menu/__init__.py
orangecontrib/esrf/oasys/__init__.py
orangecontrib/esrf/oasys/widgets/__init__.py
orangecontrib/esrf/oasys/widgets/extension/__init__.py
orangecontrib/esrf/oasys/widgets/extension/ow_surface_file_merger.py
orangecontrib/esrf/oasys/widgets/extension/icons/esrf2.png
orangecontrib/esrf/oasys/widgets/extension/icons/surface_merger.png
orangecontrib/esrf/shadow/__init__.py
orangecontrib/esrf/shadow/util/__init__.py
orangecontrib/esrf/shadow/util/conic_penelope.py
orangecontrib/esrf/shadow/util/conics_from_factory_parameters.py
orangecontrib/esrf/shadow/util/python_script.py
orangecontrib/esrf/shadow/util/shadow_objects.py
orangecontrib/esrf/shadow/util/wolter1.py
orangecontrib/esrf/shadow/widgets/__init__.py
orangecontrib/esrf/shadow/widgets/extension/__init__.py
orangecontrib/esrf/shadow/widgets/extension/ow_als_caustic.py
orangecontrib/esrf/shadow/widgets/extension/ow_conic_coefficients_mirror.py
orangecontrib/esrf/shadow/widgets/extension/ow_shadow_python_script.py
orangecontrib/esrf/shadow/widgets/extension/ow_wolter_calculator.py
orangecontrib/esrf/shadow/widgets/extension/ow_wolter_centered_calculator.py
orangecontrib/esrf/shadow/widgets/extension/icons/caustic.png
orangecontrib/esrf/shadow/widgets/extension/icons/conic_coefficients_mirror.png
orangecontrib/esrf/shadow/widgets/extension/icons/esrf.png
orangecontrib/esrf/shadow/widgets/extension/icons/esrf2.png
orangecontrib/esrf/shadow/widgets/extension/icons/hybrid_screen.png
orangecontrib/esrf/shadow/widgets/extension/icons/python_script.png
orangecontrib/esrf/shadow/widgets/extension/icons/use_wolter.png
orangecontrib/esrf/shadow/widgets/extension/icons/wolter2.png
orangecontrib/esrf/shadow/widgets/extension/miscellanea/test_first_widget.txt
orangecontrib/esrf/shadow/widgets/gui/__init__.py
orangecontrib/esrf/shadow/widgets/gui/plots.py
orangecontrib/esrf/srw/__init__.py
