Metadata-Version: 2.1
Name: OASYS1-ESRF-Extensions
Version: 0.0.94
Summary: OASYS extension for the ESRF
Home-page: https://github.com/oasys-esrf-kit/OASYS1-ESRF-Extensions
Download-URL: https://github.com/oasys-esrf-kit/OASYS1-ESRF-Extensions
Author: Manuel Sanchez del Rio, Juan Reyes-Herrera, Luca Rebuffi
Author-email: srio@esrf.eu
License: GPLv3
Keywords: raytracing,simulator,oasys1
Classifier: Development Status :: 4 - Beta
Classifier: Environment :: X11 Applications :: Qt
Classifier: Environment :: Console
Classifier: Environment :: Plugins
Classifier: Programming Language :: Python :: 3
Classifier: Intended Audience :: Science/Research
License-File: LICENSE
Requires-Dist: setuptools
Requires-Dist: oasys-barc4ro>=2024.11.13
Requires-Dist: pandas
Requires-Dist: numba
Requires-Dist: shadow4>=0.1.66
Requires-Dist: xoppylib>=1.0.30
Requires-Dist: crystalpy>=0.0.25
Requires-Dist: accelerator-toolbox==0.6.1
